talk_to_your_pc_mcp_server/__init__.py
talk_to_your_pc_mcp_server/cli.py
talk_to_your_pc_mcp_server/llm_config.py
talk_to_your_pc_mcp_server/server.py
talk_to_your_pc_mcp_server-0.1.0.dist-info/licenses/LICENSE
talk_to_your_pc_mcp_server-0.1.0.dist-info/METADATA
talk_to_your_pc_mcp_server-0.1.0.dist-info/WHEEL
talk_to_your_pc_mcp_server-0.1.0.dist-info/entry_points.txt
talk_to_your_pc_mcp_server-0.1.0.dist-info/top_level.txt
talk_to_your_pc_mcp_server-0.1.0.dist-info/RECORD
