Metadata-Version: 2.4
Name: talk-to-your-pc-mcp-server
Version: 0.1.0
Summary: MCP Server for PC system management and troubleshooting
Home-page: https://github.com/Irene-123/talk-to-your-pc-mcp-server
Author: Irene-123
Author-email: kirtipurohit025@gmail.com
Classifier: Programming Language :: Python :: 3
Classifier: License :: OSI Approved :: GNU General Public License v3 (GPLv3)
Classifier: Operating System :: OS Independent
Requires-Python: >=3.8
License-File: LICENSE
Requires-Dist: mcp>=0.1.0
Requires-Dist: openai>=1.0.0
Requires-Dist: anthropic>=0.7.0
Requires-Dist: python-dotenv>=1.0.0
Dynamic: author
Dynamic: author-email
Dynamic: classifier
Dynamic: home-page
Dynamic: license-file
Dynamic: requires-dist
Dynamic: requires-python
Dynamic: summary
